README.md
setup.py
girder_ess_dive/__init__.py
girder_ess_dive/assetstore.py
girder_ess_dive/constants.py
girder_ess_dive/rest.py
girder_ess_dive/test_essdive.py
girder_ess_dive/utils.py
girder_ess_dive.egg-info/PKG-INFO
girder_ess_dive.egg-info/SOURCES.txt
girder_ess_dive.egg-info/dependency_links.txt
girder_ess_dive.egg-info/entry_points.txt
girder_ess_dive.egg-info/requires.txt
girder_ess_dive.egg-info/top_level.txt