Metadata-Version: 2.1
Name: girder-ess-dive
Version: 1.0.0
Summary: Allows access to ESS-DIVE files through a read-only assetstore.
Home-page: https://github.com/girder/girder-ess-dive
License: UNKNOWN
Platform: UNKNOWN
Requires-Python: >=3.5
